tinyhnsw/__init__.py
tinyhnsw/filter.py
tinyhnsw/hnsw.py
tinyhnsw/index.py
tinyhnsw/knn.py
tinyhnsw/teaching/__init__.py
tinyhnsw/teaching/nsw.py
tinyhnsw/teaching/skip_list.py
tinyhnsw/utils.py
tinyhnsw/visualization.py
tinyhnsw-0.1.0.dist-info/METADATA
tinyhnsw-0.1.0.dist-info/WHEEL
tinyhnsw-0.1.0.dist-info/RECORD
