Metadata-Version: 2.1
Name: tinyhnsw
Version: 0.1.0
Summary: 
Author: Joe Barrow
Author-email: joseph.d.barrow@gmail.com
Requires-Python: >=3.11,<4.0
Classifier: Programming Language :: Python :: 3
Classifier: Programming Language :: Python :: 3.11
Classifier: Programming Language :: Python :: 3.12
Provides-Extra: examples
Requires-Dist: networkx (>=3.2.1,<4.0.0)
Requires-Dist: numpy (>=1.26.2,<2.0.0)
Requires-Dist: pillow (>=10.1.0,<11.0.0) ; extra == "examples"
Requires-Dist: requests (>=2.31.0,<3.0.0) ; extra == "examples"
Requires-Dist: sentence-transformers (>=2.2.2,<3.0.0) ; extra == "examples"
Requires-Dist: tqdm (>=4.66.1,<5.0.0)
Requires-Dist: transformers (>=4.35.2,<5.0.0) ; extra == "examples"
